caikit_nlp_client/__init__.py
caikit_nlp_client/_version.py
caikit_nlp_client/grpc_client.py
caikit_nlp_client/http_client.py
caikit_nlp_client/utils.py
caikit_nlp_client-0.0.8.dist-info/LICENSE
caikit_nlp_client-0.0.8.dist-info/METADATA
caikit_nlp_client-0.0.8.dist-info/WHEEL
caikit_nlp_client-0.0.8.dist-info/top_level.txt
caikit_nlp_client-0.0.8.dist-info/RECORD
