Metadata-Version: 2.1
Name: caikit-nlp-client
Version: 0.0.8
Summary: caikit-nlp client
Author-email: Vaibhav Jain <vajain@redhat.com>, Laurentiu Bradin <laurentiu.bradin@ibm.com>, Daniele Trifirò <dtrifiro@redhat.com>
License: Apache License 2.0
Project-URL: Source, https://github.com/opendatahub-io/caikit-nlp-client/
Classifier: License :: OSI Approved :: Apache Software License
Classifier: Development Status :: 4 - Beta
Classifier: Programming Language :: Python :: 3
Classifier: Programming Language :: Python :: 3.9
Classifier: Programming Language :: Python :: 3.10
Classifier: Programming Language :: Python :: 3.11
Requires-Python: >=3.9
License-File: LICENSE
Requires-Dist: grpcio-reflection ==1.59.3
Requires-Dist: requests ==2.31.0
Provides-Extra: dev
Requires-Dist: ruff ==0.1.7 ; extra == 'dev'
Requires-Dist: grpcio-tools ==1.59.3 ; extra == 'dev'
Requires-Dist: caikit-nlp-client[types] ; extra == 'dev'
Provides-Extra: tests
Requires-Dist: pytest ; extra == 'tests'
Requires-Dist: pytest-cov ; extra == 'tests'
Requires-Dist: pytest-docker ; extra == 'tests'
Requires-Dist: pytest-mock ; extra == 'tests'
Requires-Dist: coverage[toml] ; extra == 'tests'
Requires-Dist: grpcio-health-checking ; extra == 'tests'
Requires-Dist: caikit[runtime-grpc,runtime-http] <0.26.0,>=0.23.2 ; extra == 'tests'
Provides-Extra: types
Requires-Dist: mypy ==1.7.1 ; extra == 'types'
Requires-Dist: types-requests ==2.31.0.10 ; extra == 'types'
Requires-Dist: types-protobuf ==4.24.0.4 ; extra == 'types'
